topbar_hub_buttons/__init__.py
topbar_hub_buttons/_version.py
topbar_hub_buttons-0.2.1.data/data/share/jupyter/labextensions/topbar-hub-buttons/package.json
topbar_hub_buttons-0.2.1.data/data/share/jupyter/labextensions/topbar-hub-buttons/static/282.546bd1e2dbfe9e378165.js
topbar_hub_buttons-0.2.1.data/data/share/jupyter/labextensions/topbar-hub-buttons/static/568.b1981b58a5969c5ea08a.js
topbar_hub_buttons-0.2.1.data/data/share/jupyter/labextensions/topbar-hub-buttons/static/remoteEntry.0260b561c2a900b5db1f.js
topbar_hub_buttons-0.2.1.data/data/share/jupyter/labextensions/topbar-hub-buttons/static/style.js
topbar_hub_buttons-0.2.1.data/data/share/jupyter/labextensions/topbar-hub-buttons/static/third-party-licenses.json
topbar_hub_buttons-0.2.1.data/data/share/jupyter/labextensions/topbar-hub-buttons/install.json
topbar_hub_buttons-0.2.1.dist-info/METADATA
topbar_hub_buttons-0.2.1.dist-info/WHEEL
topbar_hub_buttons-0.2.1.dist-info/licenses/LICENSE
topbar_hub_buttons-0.2.1.dist-info/RECORD
