Metadata-Version: 2.3
Name: topbar_hub_buttons
Version: 0.2.1
Dynamic: Keywords
Summary: A JupyterLab extension that adds JupyterHub buttons on the topbar
Project-URL: Homepage, https://github.com/AaltoSciComp/topbar-hub-buttons
Project-URL: Bug Tracker, https://github.com/AaltoSciComp/topbar-hub-buttons/issues
Project-URL: Repository, https://github.com/Gehock/topbar-hub-buttons
Author-email: AlirezaT99 <alireza.tajmirriahi@aalto.fi>
License: BSD 3-Clause License
License-File: LICENSE
Classifier: Framework :: Jupyter
Classifier: Framework :: Jupyter :: JupyterLab
Classifier: Framework :: Jupyter :: JupyterLab :: 4
Classifier: Framework :: Jupyter :: JupyterLab :: Extensions
Classifier: Framework :: Jupyter :: JupyterLab :: Extensions :: Prebuilt
Classifier: License :: OSI Approved :: BSD License
Classifier: Programming Language :: Python
Classifier: Programming Language :: Python :: 3
Classifier: Programming Language :: Python :: 3.8
Classifier: Programming Language :: Python :: 3.9
Classifier: Programming Language :: Python :: 3.10
Classifier: Programming Language :: Python :: 3.11
Requires-Python: >=3.8
